fireblocks/__init__.py
fireblocks/additional_options.py
fireblocks/api_client.py
fireblocks/api_response.py
fireblocks/base_path.py
fireblocks/bearer_token_provider.py
fireblocks/client.py
fireblocks/client_configuration.py
fireblocks/configuration.py
fireblocks/exceptions.py
fireblocks/py.typed
fireblocks/rest.py
fireblocks/threaded_api_client.py
fireblocks/unknown_model.py
fireblocks/user_agent_util.py
fireblocks/validation_utils.py
fireblocks/api/__init__.py
fireblocks/api/api_user_api.py
fireblocks/api/assets_api.py
fireblocks/api/audit_logs_api.py
fireblocks/api/blockchains_assets_api.py
fireblocks/api/compliance_api.py
fireblocks/api/compliance_screening_configuration_api.py
fireblocks/api/connected_accounts_beta_api.py
fireblocks/api/console_user_api.py
fireblocks/api/contract_interactions_api.py
fireblocks/api/contract_templates_api.py
fireblocks/api/contracts_api.py
fireblocks/api/cosigners_beta_api.py
fireblocks/api/deployed_contracts_api.py
fireblocks/api/embedded_wallets_api.py
fireblocks/api/exchange_accounts_api.py
fireblocks/api/external_wallets_api.py
fireblocks/api/fiat_accounts_api.py
fireblocks/api/gas_stations_api.py
fireblocks/api/internal_wallets_api.py
fireblocks/api/job_management_api.py
fireblocks/api/key_link_beta_api.py
fireblocks/api/keys_beta_api.py
fireblocks/api/network_connections_api.py
fireblocks/api/nfts_api.py
fireblocks/api/off_exchanges_api.py
fireblocks/api/ota_beta_api.py
fireblocks/api/payments_payout_api.py
fireblocks/api/policy_editor_beta_api.py
fireblocks/api/policy_editor_v2_beta_api.py
fireblocks/api/reset_device_api.py
fireblocks/api/smart_transfer_api.py
fireblocks/api/staking_api.py
fireblocks/api/tags_api.py
fireblocks/api/tokenization_api.py
fireblocks/api/trading_beta_api.py
fireblocks/api/transactions_api.py
fireblocks/api/travel_rule_api.py
fireblocks/api/user_groups_beta_api.py
fireblocks/api/users_api.py
fireblocks/api/vaults_api.py
fireblocks/api/web3_connections_api.py
fireblocks/api/webhooks_api.py
fireblocks-13.0.0.dist-info/licenses/LICENSE.txt
fireblocks-13.0.0.dist-info/METADATA
fireblocks-13.0.0.dist-info/WHEEL
fireblocks-13.0.0.dist-info/top_level.txt
fireblocks-13.0.0.dist-info/RECORD
