Metadata-Version: 2.4
Name: fireblocks
Version: 13.0.0
Summary: Fireblocks API
Home-page: https://github.com/fireblocks/py-sdk/tree/master
Author: Fireblocks
Author-email: support@fireblocks.com
License: MIT License
Keywords: Fireblocks,SDK,Fireblocks API
Classifier: Development Status :: 5 - Production/Stable
Classifier: Intended Audience :: Developers
Classifier: Topic :: Software Development
Classifier: License :: OSI Approved :: MIT License
Classifier: Programming Language :: Python :: 3.8
Requires-Python: >= 3.8
License-File: LICENSE.txt
Requires-Dist: urllib3<3.0.0,>=2.1.0
Requires-Dist: python-dateutil>=2.8.2
Requires-Dist: pydantic>=2
Requires-Dist: typing-extensions>=4.7.1
Requires-Dist: PyJWT>=2.3.0
Requires-Dist: cryptography>=2.7
Dynamic: author
Dynamic: author-email
Dynamic: classifier
Dynamic: description
Dynamic: description-content-type
Dynamic: home-page
Dynamic: keywords
Dynamic: license
Dynamic: license-file
Dynamic: requires-dist
Dynamic: requires-python
Dynamic: summary
